LICENSE
MANIFEST.in
README.md
setup.py
refman/__init__.py
refman/_app.py
refman/_bibpain.py
refman/_constants.py
refman/_scihub.py
refman/_utils.py
refman/refman.py
refman.egg-info/PKG-INFO
refman.egg-info/SOURCES.txt
refman.egg-info/dependency_links.txt
refman.egg-info/entry_points.txt
refman.egg-info/not-zip-safe
refman.egg-info/requires.txt
refman.egg-info/top_level.txt
refman/templates/index.html