Metadata-Version: 2.1
Name: refman
Version: 0.0.2
Summary: RefMan - A Simple python-based reference manager
Home-page: https://github.com/adriancaruana/refman
Author: Adrian Caruana
Author-email: adrian@adriancaruana.com
License: MIT
Keywords: Reference,Manager,BibTeX,crossref
Platform: UNKNOWN
Classifier: License :: OSI Approved :: MIT License
Classifier: Programming Language :: Python :: 3.9
License-File: LICENSE
